cimiss/__init__.py
cimiss/client.py
cimiss/stub.ice
cimiss/stub_ice.py
cimiss/cma/__init__.py
cimiss/cma/cimiss/__init__.py
cimiss_python-0.1.8.data/data/cimiss/stub.ice
cimiss_python-0.1.8.dist-info/LICENSE
cimiss_python-0.1.8.dist-info/METADATA
cimiss_python-0.1.8.dist-info/WHEEL
cimiss_python-0.1.8.dist-info/top_level.txt
cimiss_python-0.1.8.dist-info/RECORD
